{
    "authd": {
        "url": "http://localhost:27183",
        "serverName": "authd.tidepay.io"
    },
    "blobvault": {
        "host": "localhost:27182"
    },
    "isunpayrpc": {
        "url": "http://rpc:27184"
    },
    "blobvaultDatabase": {
        "host": "postgresql",
        "user": "docker",
        "database": "blobvault_docker"
    },
    "fileDatabase": {
        "host": "mongodb",
        "port": 27017,
        "database": "blobvaultfile_docker",
        "options": {
            "user": "blobvault",
            "pass": "password",
            "auth": {
                "authdb": "blobvaultfile_docker"
            }
        }
    },
    "journalDatabase": {
        "host": "mongodb",
        "port": 27017,
        "database": "dataapifile_docker",
        "options": {
            "user": "dataapi",
            "pass": "password",
            "auth": {
                "authdb": "dataapifile_docker"
            }
        }
    },
    "email": {
        "subjectPrefix": "[Docker] "
    }
}
